setup.py
src/infi/__init__.py
src/infi.rdc.egg-info/PKG-INFO
src/infi.rdc.egg-info/SOURCES.txt
src/infi.rdc.egg-info/dependency_links.txt
src/infi.rdc.egg-info/entry_points.txt
src/infi.rdc.egg-info/namespace_packages.txt
src/infi.rdc.egg-info/not-zip-safe
src/infi.rdc.egg-info/requires.txt
src/infi.rdc.egg-info/top_level.txt
src/infi/rdc/__init__.py
src/infi/rdc/__version__.py